multisys/__init__.py
multisys/entry.py
multisys-0.1.dist-info/LICENSE.txt
multisys-0.1.dist-info/METADATA
multisys-0.1.dist-info/WHEEL
multisys-0.1.dist-info/entry_points.txt
multisys-0.1.dist-info/top_level.txt
multisys-0.1.dist-info/RECORD
